b2tob64/__init__.py
b2tob64/b2tob64.py
b2tob64-2.0.0.dist-info/METADATA
b2tob64-2.0.0.dist-info/WHEEL
b2tob64-2.0.0.dist-info/licenses/LICENSE
b2tob64-2.0.0.dist-info/RECORD
