Metadata-Version: 2.3
Name: b2tob64
Version: 2.0.0
Summary: Custom converting b2/b42 to and from b64/b2
Project-URL: Homepage, https://github.com/vjgtigers/b2tob64
Project-URL: Bug Tracker, https://github.com/vjgtigers/b2tob64/issues
Author-email: Vaughn Gugger <vjgtigers@gmail.com>
License-File: LICENSE
Classifier: License :: OSI Approved :: MIT License
Classifier: Operating System :: OS Independent
Classifier: Programming Language :: Python :: 3
Requires-Python: >=3.10
